dataanalysiscompare/__init__.py
dataanalysiscompare/main.py
dataanalysiscompare/prompts.py
dataanalysiscompare-2025.12.21103520.dist-info/METADATA
dataanalysiscompare-2025.12.21103520.dist-info/WHEEL
dataanalysiscompare-2025.12.21103520.dist-info/top_level.txt
dataanalysiscompare-2025.12.21103520.dist-info/RECORD
