Metadata-Version: 2.4
Name: dataanalysiscompare
Version: 2025.12.21103520
Summary: A new package that helps users compare and choose the right data analysis tool by providing structured, expert-level insights. Users input their specific data analysis needs, project requirements, or 
Author-email: dataanalysiscompare <hi@eugene.plus>
License: MIT
Project-URL: Homepage, https://github.com/chigwell/dataanalysiscompare
Requires-Python: >=3.9
Requires-Dist: langchain-llm7>=0.0.0
Requires-Dist: llmatch-messages>=0.0.0
Requires-Dist: langchain-core>=0.3.0
